setup.py
LBIndex.egg-info/PKG-INFO
LBIndex.egg-info/SOURCES.txt
LBIndex.egg-info/dependency_links.txt
LBIndex.egg-info/requires.txt
LBIndex.egg-info/top_level.txt
lbindex/__init__.py
lbindex/__main__.py
lbindex/app.py
lbindex/scripts/__init__.py
lbindex/scripts/buscabases.py
lbindex/scripts/buscaregistro.py
lbindex/scripts/indexa.py